README.md
pyproject.toml
setup.py
src/improve/__init__.py
src/improve/functools.py
src/improve.egg-info/PKG-INFO
src/improve.egg-info/SOURCES.txt
src/improve.egg-info/dependency_links.txt
src/improve.egg-info/entry_points.txt
src/improve.egg-info/top_level.txt
src/improve/logging/__init__.py
src/improve/logging/decorators.py
src/improve/logging/formatters.py
src/improve/logging/handlers.py
src/improve/utils/__init__.py
src/improve/utils/chmtime.py
src/improve/utils/waituntil.py